ampel/abstract/AbsLightCurveT2Unit.py
ampel/abstract/AbsPhotoT3Unit.py
ampel/abstract/AbsT2Tabulator.py
ampel/abstract/AbsTabulatedT2Unit.py
ampel/abstract/AbsTiedLightCurveT2Unit.py
ampel/aux/PPSFilter.py
ampel/aux/ULSFilter.py
ampel/demo/DemoEvery3PhotoPointT2Unit.py
ampel/demo/DemoEvery4PhotoPointT2Unit.py
ampel/demo/DemoFirstPhotoPointT2Unit.py
ampel/demo/DemoFirstUpperLimitT2Unit.py
ampel/demo/DemoLightCurveT2Unit.py
ampel/demo/DemoPhotoPointT2Unit.py
ampel/demo/DemoTiedLightCurveT2Unit.py
ampel/py.typed
ampel/t1/T1PhotoRetroCombiner.py
ampel/view/LightCurve.py
ampel/view/TransientView.py
conf/ampel-photometry/ampel.yaml
ampel_photometry-0.10.1.dist-info/METADATA
ampel_photometry-0.10.1.dist-info/WHEEL
ampel_photometry-0.10.1.dist-info/RECORD
