Metadata-Version: 2.1
Name: ampel-photometry
Version: 0.10.1
Summary: Photometry add-on for the Ampel system
License: BSD-3-Clause
Author: Valery Brinnel
Requires-Python: >=3.10,<4.0
Classifier: License :: OSI Approved :: BSD License
Classifier: Programming Language :: Python :: 3
Classifier: Programming Language :: Python :: 3.10
Classifier: Programming Language :: Python :: 3.11
Classifier: Programming Language :: Python :: 3.12
Classifier: Programming Language :: Python :: 3.13
Requires-Dist: ampel-interface (>=0.10.4.post0,<0.11)
Requires-Dist: astropy (>=5)
